fastapi_backports/__init__.py
fastapi_backports/_backporter.py
fastapi_backports/_retyped.py
fastapi_backports/apply.py
fastapi_backports/_backports/__init__.py
fastapi_backports/_backports/_base.py
fastapi_backports/_backports/lifespan_decorator.py
fastapi_backports/_backports/multiple_query_models.py
fastapi_backports/_backports/postponed_annotations.py
fastapi_backports/_backports/query_method.py
fastapi_backports/_backports/route_middleware.py
fastapi_backports/_backports/type_alias_type.py
fastapi_backports-0.1.3.dist-info/METADATA
fastapi_backports-0.1.3.dist-info/WHEEL
fastapi_backports-0.1.3.dist-info/licenses/LICENSE
fastapi_backports-0.1.3.dist-info/RECORD
